tests/core/__init__.py
tests/core/test_client.py
tests/type/__init__.py
tests/type/test_wos.py
wos_sdk/__init__.py
wos_sdk/cli/__init__.py
wos_sdk/cli/cli.py
wos_sdk/core/__init__.py
wos_sdk/core/client.py
wos_sdk/core/connection.py
wos_sdk/core/http.py
wos_sdk/core/service.py
wos_sdk/transport/__init__.py
wos_sdk/transport/transport.py
wos_sdk/type/__init__.py
wos_sdk/type/constant.py
wos_sdk/type/wos.py
wos_sdk/utils/__init__.py
wos_sdk/utils/logger.py
wos_sdk-0.1.2.dist-info/LICENSE
wos_sdk-0.1.2.dist-info/METADATA
wos_sdk-0.1.2.dist-info/WHEEL
wos_sdk-0.1.2.dist-info/entry_points.txt
wos_sdk-0.1.2.dist-info/top_level.txt
wos_sdk-0.1.2.dist-info/RECORD
