Metadata-Version: 2.1
Name: wos-sdk
Version: 0.1.2
Summary: Python SDK for interacting with WinGs Operating System
Home-page: UNKNOWN
Author: WinGs Robotics
Author-email: dev@wingsrobotics.com
License: UNKNOWN
Platform: UNKNOWN
License-File: LICENSE
Requires-Dist: requests
Requires-Dist: websocket-client
